senzing/__init__.py
senzing/constants.py
senzing/py.typed
senzing/szabstractfactory.py
senzing/szconfig.py
senzing/szconfigmanager.py
senzing/szdiagnostic.py
senzing/szengine.py
senzing/szengineflags.py
senzing/szerror.py
senzing/szhelpers.py
senzing/szproduct.py
senzing-4.1.0.dist-info/licenses/LICENSE
senzing-4.1.0.dist-info/licenses/.github/senzing-corporate-contributor-license-agreement.pdf
senzing-4.1.0.dist-info/licenses/.github/senzing-individual-contributor-license-agreement.pdf
senzing_mock/__init__.py
senzing_mock/senzing_mock.py
senzing_truthset/__init__.py
senzing_truthset/customers.py
senzing_truthset/datasources.py
senzing_truthset/py.typed
senzing_truthset/references.py
senzing_truthset/watchlist.py
senzing-4.1.0.dist-info/METADATA
senzing-4.1.0.dist-info/WHEEL
senzing-4.1.0.dist-info/top_level.txt
senzing-4.1.0.dist-info/RECORD
