Metadata-Version: 2.4
Name: senzing
Version: 4.1.0
Summary: Python SDK method definitions
Author-email: senzing <support@senzing.com>
License-Expression: Apache-2.0
Project-URL: bugtracker, https://github.com/senzing-garage/sz-sdk-python/issues
Project-URL: changelog, https://github.com/senzing-garage/sz-sdk-python/blob/main/CHANGELOG.md
Project-URL: source, https://github.com/senzing-garage/sz-sdk-python
Classifier: Programming Language :: Python :: 3
Classifier: Operating System :: OS Independent
Requires-Python: >=3.10
License-File: LICENSE
License-File: .github/senzing-corporate-contributor-license-agreement.pdf
License-File: .github/senzing-individual-contributor-license-agreement.pdf
Dynamic: license-file
